[{"__type__":"cc.SpriteFrame","content":{"name":"hit02","texture":"52kuXVQeZFlINN2ZMcvWq8","rect":[129,798,258,71],"offset":[10,-63],"originalSize":[316,197]}},{"__type__":"cc.SpriteFrame","content":{"name":"swim14","texture":"52kuXVQeZFlINN2ZMcvWq8","rect":[483,401,268,65],"offset":[22,-49],"originalSize":[316,197],"rotated":1}},{"__type__":"cc.SpriteFrame","content":{"name":"die10","texture":"52kuXVQeZFlINN2ZMcvWq8","rect":[774,135,232,129],"offset":[-21,-17],"originalSize":[316,197]}},{"__type__":"cc.SpriteFrame","content":{"name":"swim03","texture":"52kuXVQeZFlINN2ZMcvWq8","rect":[129,723,250,73],"offset":[13,-56],"originalSize":[316,197]}},{"__type__":"cc.SpriteFrame","content":{"name":"hit07","texture":"52kuXVQeZFlINN2ZMcvWq8","rect":[460,671,254,71],"offset":[20,-34],"originalSize":[316,197],"rotated":1}},{"__type__":"cc.SpriteFrame","content":{"name":"swim08","texture":"52kuXVQeZFlINN2ZMcvWq8","rect":[696,477,268,67],"offset":[21,-44],"originalSize":[316,197]}},{"__type__":"cc.SpriteFrame","content":{"name":"swim13","texture":"52kuXVQeZFlINN2ZMcvWq8","rect":[736,266,270,65],"offset":[23,-48],"originalSize":[316,197]}},{"__type__":"cc.SpriteFrame","content":{"name":"die09","texture":"52kuXVQeZFlINN2ZMcvWq8","rect":[534,145,240,119],"offset":[-12,-18],"originalSize":[316,197],"rotated":1}},{"__type__":"cc.SpriteFrame","content":{"name":"hit09","texture":"52kuXVQeZFlINN2ZMcvWq8","rect":[696,546,268,65],"offset":[24,-45],"originalSize":[316,197]}},{"__type__":"cc.SpriteFrame","content":{"name":"hit03","texture":"52kuXVQeZFlINN2ZMcvWq8","rect":[533,671,262,57],"offset":[9,-52],"originalSize":[316,197],"rotated":1}},{"__type__":"cc.SpriteFrame","content":{"name":"die11","texture":"52kuXVQeZFlINN2ZMcvWq8","rect":[774,2,232,131],"offset":[-31,-17],"originalSize":[316,197]}},{"__type__":"cc.SpriteFrame","content":{"name":"die03","texture":"52kuXVQeZFlINN2ZMcvWq8","rect":[258,2,262,147],"offset":[15,-9],"originalSize":[316,197]}},{"__type__":"cc.SpriteFrame","content":{"name":"hit06","texture":"52kuXVQeZFlINN2ZMcvWq8","rect":[621,407,256,73],"offset":[19,-32],"originalSize":[316,197],"rotated":1}},{"__type__":"cc.SpriteFrame","content":{"name":"die12","texture":"52kuXVQeZFlINN2ZMcvWq8","rect":[2,699,238,125],"offset":[-37,-20],"originalSize":[316,197],"rotated":1}},{"__type__":"cc.SpriteFrame","content":{"name":"swim07","texture":"52kuXVQeZFlINN2ZMcvWq8","rect":[736,333,266,73],"offset":[19,-49],"originalSize":[316,197]}},{"__type__":"cc.SpriteFrame","content":{"name":"hit04","texture":"52kuXVQeZFlINN2ZMcvWq8","rect":[659,812,266,57],"offset":[13,-46],"originalSize":[316,197]}},{"__type__":"cc.SpriteFrame","content":{"name":"swim02","texture":"52kuXVQeZFlINN2ZMcvWq8","rect":[402,401,256,79],"offset":[15,-57],"originalSize":[316,197],"rotated":1}},{"__type__":"cc.SpriteFrame","content":{"name":"die15","texture":"52kuXVQeZFlINN2ZMcvWq8","rect":[151,439,276,95],"offset":[-20,-34],"originalSize":[316,197],"rotated":1}},{"__type__":"cc.SpriteFrame","content":{"name":"swim05","texture":"52kuXVQeZFlINN2ZMcvWq8","rect":[659,871,254,63],"offset":[14,-50],"originalSize":[316,197]}},{"__type__":"cc.SpriteFrame","content":{"name":"hit08","texture":"52kuXVQeZFlINN2ZMcvWq8","rect":[659,747,262,63],"offset":[24,-40],"originalSize":[316,197]}},{"__type__":"cc.SpriteFrame","content":{"name":"hit05","texture":"52kuXVQeZFlINN2ZMcvWq8","rect":[659,680,262,65],"offset":[18,-38],"originalSize":[316,197]}},{"__type__":"cc.SpriteFrame","content":{"name":"die14","texture":"52kuXVQeZFlINN2ZMcvWq8","rect":[169,175,262,107],"offset":[-27,-28],"originalSize":[316,197],"rotated":1}},{"__type__":"cc.SpriteFrame","content":{"name":"hit01","texture":"52kuXVQeZFlINN2ZMcvWq8","rect":[321,397,260,79],"offset":[18,-58],"originalSize":[316,197],"rotated":1}},{"__type__":"cc.SpriteFrame","content":{"name":"die05","texture":"52kuXVQeZFlINN2ZMcvWq8","rect":[2,175,260,165],"offset":[23,16],"originalSize":[316,197],"rotated":1}},{"__type__":"cc.SpriteFrame","content":{"name":"swim09","texture":"52kuXVQeZFlINN2ZMcvWq8","rect":[550,387,268,69],"offset":[21,-45],"originalSize":[316,197],"rotated":1}},{"__type__":"cc.SpriteFrame","content":{"name":"swim06","texture":"52kuXVQeZFlINN2ZMcvWq8","rect":[129,871,262,69],"offset":[17,-49],"originalSize":[316,197]}},{"__type__":"cc.SpriteFrame","content":{"name":"die08","texture":"52kuXVQeZFlINN2ZMcvWq8","rect":[278,151,244,133],"offset":[-1,-3],"originalSize":[316,197],"rotated":1}},{"__type__":"cc.SpriteFrame","content":{"name":"swim11","texture":"52kuXVQeZFlINN2ZMcvWq8","rect":[393,659,266,65],"offset":[21,-45],"originalSize":[316,197],"rotated":1}},{"__type__":"cc.SpriteAtlas","_name":"fishes19.plist","_spriteFrames":{"die01":{"__uuid__":"b9rxDS4qhBmKo9Vwkew5VL"},"die02":{"__uuid__":"d7ptJyW7VLy4PVp/BBS+nX"},"die03":{"__uuid__":"63DjqcTAVBAITkB5yoaJtT"},"die04":{"__uuid__":"d1P7OUvp5BfbA7XFLivZbK"},"die05":{"__uuid__":"a0toVpebBPnZsLbXvNSPoe"},"die06":{"__uuid__":"d3ULtdp0BKXq7JNmaPWkbH"},"die07":{"__uuid__":"d70yMdF4JDg5ldl7PiyuwT"},"die08":{"__uuid__":"a9ahC/T7pD0ZD/okzkxTB2"},"die09":{"__uuid__":"44ub0MuKBLmqETy9JfW3kO"},"die10":{"__uuid__":"0fe9wFaPNOcLBQQsKmT3t2"},"die11":{"__uuid__":"626jLMKAVErYe21DvMdFSD"},"die12":{"__uuid__":"65nmnjmDdAo57zupVN7NKX"},"die13":{"__uuid__":"b1hMt3ZY5Hy4unbJnJWhmQ"},"die14":{"__uuid__":"9c0NyzQYBDJJHUys52CSAu"},"die15":{"__uuid__":"819TxbDyFD4aDGH9SRBTal"},"hit01":{"__uuid__":"a0A6YiiQRB2bpUax7ZLhxE"},"hit02":{"__uuid__":"01ckv8ZhFPVopWm6t4Ksy7"},"hit03":{"__uuid__":"59DOKpZodAj5L0j0hmxh2s"},"hit04":{"__uuid__":"6874eeLNRJf5t5xPHCaLFQ"},"hit05":{"__uuid__":"9cipYk4M5NGowhAOQYat6M"},"hit06":{"__uuid__":"65Dqogg4NN2IqpjhG2NGue"},"hit07":{"__uuid__":"31jUrBlnxItLL5oaTFKAKD"},"hit08":{"__uuid__":"8aQ+BvhKpDrr88ha1ky67g"},"hit09":{"__uuid__":"4b1HkVWoRIeYd9Q91OPElC"},"swim01":{"__uuid__":"dfy2eGS9VHxK40xNnWLom+"},"swim02":{"__uuid__":"73lzAv3xFC65L8Op/mMxYc"},"swim03":{"__uuid__":"2aVZShN2pBTbE9prJ9KNRk"},"swim04":{"__uuid__":"edCzKE2gZD2YDr7oFr+S9u"},"swim05":{"__uuid__":"85XxH1YR1CM76/upodIIBR"},"swim06":{"__uuid__":"a9MxD7ywtKobWgkNsXvJ6i"},"swim07":{"__uuid__":"658i3ZwRNF6YnnszicJEw8"},"swim08":{"__uuid__":"3aTt0GqqdBWInuSBB8oisZ"},"swim09":{"__uuid__":"a8QBBfGJZB16lx+VzOz2wy"},"swim10":{"__uuid__":"f0gSg4jbVAR7UWsAQBmttp"},"swim11":{"__uuid__":"ab6yJVVVpN1Io1qg3eD6WZ"},"swim12":{"__uuid__":"eaHipz8StKAJlkgAhvpB0F"},"swim13":{"__uuid__":"42443ZjlREoar3mBJuAYlo"},"swim14":{"__uuid__":"04XC221lhLj6PDs0ayWSMQ"}}},{"__type__":"cc.SpriteFrame","content":{"name":"die13","texture":"52kuXVQeZFlINN2ZMcvWq8","rect":[413,151,248,119],"offset":[-34,-23],"originalSize":[316,197],"rotated":1}},{"__type__":"cc.SpriteFrame","content":{"name":"die01","texture":"52kuXVQeZFlINN2ZMcvWq8","rect":[696,613,268,65],"offset":[22,-43],"originalSize":[316,197]}},{"__type__":"cc.SpriteFrame","content":{"name":"die04","texture":"52kuXVQeZFlINN2ZMcvWq8","rect":[2,2,254,171],"offset":[17,8],"originalSize":[316,197]}},{"__type__":"cc.SpriteFrame","content":{"name":"die06","texture":"52kuXVQeZFlINN2ZMcvWq8","rect":[2,437,260,147],"offset":[22,23],"originalSize":[316,197],"rotated":1}},{"__type__":"cc.SpriteFrame","content":{"name":"die02","texture":"52kuXVQeZFlINN2ZMcvWq8","rect":[248,439,282,71],"offset":[15,-22],"originalSize":[316,197],"rotated":1}},{"__type__":"cc.SpriteFrame","content":{"name":"die07","texture":"52kuXVQeZFlINN2ZMcvWq8","rect":[522,2,250,141],"offset":[11,13],"originalSize":[316,197]}},{"__type__":"cc.SpriteFrame","content":{"name":"swim01","texture":"52kuXVQeZFlINN2ZMcvWq8","rect":[655,145,260,79],"offset":[18,-58],"originalSize":[316,197],"rotated":1}},{"__type__":"cc.SpriteFrame","content":{"name":"swim12","texture":"52kuXVQeZFlINN2ZMcvWq8","rect":[696,408,268,67],"offset":[22,-46],"originalSize":[316,197]}},{"__type__":"cc.SpriteFrame","content":{"name":"swim04","texture":"52kuXVQeZFlINN2ZMcvWq8","rect":[927,680,250,67],"offset":[13,-52],"originalSize":[316,197],"rotated":1}},{"__type__":"cc.SpriteFrame","content":{"name":"swim10","texture":"52kuXVQeZFlINN2ZMcvWq8","rect":[592,665,266,65],"offset":[20,-44],"originalSize":[316,197],"rotated":1}}]