[{"__type__":"cc.AnimationClip","_name":"fish13","_duration":0.65,"sample":20,"wrapMode":2,"curveData":{"comps":{"cc.Sprite":{"spriteFrame":[{"frame":0,"value":{"__uuid__":"d9YBe8NqxGAaVdz5Fw21cj"}},{"frame":0.05,"value":{"__uuid__":"06wae9ohhHK63nzFD/kEt7"}},{"frame":0.1,"value":{"__uuid__":"85o8LF3uhBHoAMfuj+3wLA"}},{"frame":0.15,"value":{"__uuid__":"deSFlL+PFMEa+zGJdWU/3g"}},{"frame":0.2,"value":{"__uuid__":"11G63sEOVGh6fG4rMdlG0d"}},{"frame":0.25,"value":{"__uuid__":"d7IEocOCtGRZpUyMPFjsPv"}},{"frame":0.3,"value":{"__uuid__":"57Tzrm/SFPYIGYsWIVu7uN"}},{"frame":0.35,"value":{"__uuid__":"1epgHoD09APZdtNdlinEhH"}},{"frame":0.4,"value":{"__uuid__":"37iW3J8lJADoiFUALzsr8Q"}},{"frame":0.45,"value":{"__uuid__":"e2Qx2L0X9HeYNDSnuO0MyK"}},{"frame":0.5,"value":{"__uuid__":"7cfn5iVsdOAbirt4Q8Ndki"}},{"frame":0.55,"value":{"__uuid__":"22kWfb1ytJl6NCUvc5FmS4"}},{"frame":0.6,"value":{"__uuid__":"c8kYMD2Q1BFZGBTbHS3hjo"}}]}}}},{"__type__":"cc.SpriteFrame","content":{"name":"hm_swim00002","texture":"0eNw1JlzRKuaxCIhAq6sc8","rect":[91,952,39,87],"offset":[-2,-1],"originalSize":[49,91],"rotated":1}},{"__type__":"cc.SpriteFrame","content":{"name":"hm_swim00005","texture":"0eNw1JlzRKuaxCIhAq6sc8","rect":[650,859,43,87],"offset":[-2,1],"originalSize":[49,91],"rotated":1}},{"__type__":"cc.SpriteFrame","content":{"name":"hm_swim00008","texture":"0eNw1JlzRKuaxCIhAq6sc8","rect":[650,772,47,85],"offset":[-1,0],"originalSize":[49,91]}},{"__type__":"cc.SpriteFrame","content":{"name":"hm_swim00012","texture":"0eNw1JlzRKuaxCIhAq6sc8","rect":[386,911,43,87],"offset":[-3,-2],"originalSize":[49,91],"rotated":1}},{"__type__":"cc.SpriteFrame","content":{"name":"hm_swim00009","texture":"0eNw1JlzRKuaxCIhAq6sc8","rect":[2,944,47,87],"offset":[-1,0],"originalSize":[49,91],"rotated":1}},{"__type__":"cc.SpriteFrame","content":{"name":"hm_swim00007","texture":"0eNw1JlzRKuaxCIhAq6sc8","rect":[603,780,45,87],"offset":[-2,1],"originalSize":[49,91]}},{"__type__":"cc.SpriteFrame","content":{"name":"hm_swim00011","texture":"0eNw1JlzRKuaxCIhAq6sc8","rect":[793,770,43,87],"offset":[-2,-1],"originalSize":[49,91]}},{"__type__":"cc.SpriteFrame","content":{"name":"hm_swim00003","texture":"0eNw1JlzRKuaxCIhAq6sc8","rect":[865,611,39,87],"offset":[-2,0],"originalSize":[49,91]}},{"__type__":"cc.SpriteFrame","content":{"name":"hm_swim00013","texture":"0eNw1JlzRKuaxCIhAq6sc8","rect":[267,956,41,87],"offset":[-2,-2],"originalSize":[49,91],"rotated":1}},{"__type__":"cc.SpriteFrame","content":{"name":"hm_swim00006","texture":"0eNw1JlzRKuaxCIhAq6sc8","rect":[746,770,45,85],"offset":[-2,1],"originalSize":[49,91]}},{"__type__":"cc.SpriteFrame","content":{"name":"hm_swim00001","texture":"0eNw1JlzRKuaxCIhAq6sc8","rect":[650,904,39,87],"offset":[-2,-1],"originalSize":[49,91],"rotated":1}},{"__type__":"cc.SpriteFrame","content":{"name":"hm_swim00004","texture":"0eNw1JlzRKuaxCIhAq6sc8","rect":[356,956,41,87],"offset":[-3,1],"originalSize":[49,91],"rotated":1}},{"__type__":"cc.SpriteFrame","content":{"name":"hm_swim00010","texture":"0eNw1JlzRKuaxCIhAq6sc8","rect":[699,772,45,85],"offset":[-2,-1],"originalSize":[49,91]}}]